nist_nvd/__init__.py
nist_nvd/__main__.py
nist_nvd/config.py
nist_nvd/py.typed
nist_nvd/validator.py
nist_nvd-0.1.7.dist-info/METADATA
nist_nvd-0.1.7.dist-info/WHEEL
nist_nvd-0.1.7.dist-info/entry_points.txt
nist_nvd-0.1.7.dist-info/top_level.txt
nist_nvd-0.1.7.dist-info/RECORD
